aclsum-0.1.2.dist-info/METADATA
aclsum-0.1.2.dist-info/WHEEL
aclsum/.DS_Store
aclsum/__init__.py
aclsum/aclsum.py
aclsum/dataset/paper_jsons/2020.aacl-main.33.json
aclsum/dataset/paper_jsons/2020.aacl-main.67.json
aclsum/dataset/paper_jsons/2020.aacl-main.88.json
aclsum/dataset/paper_jsons/2020.acl-main.282.json
aclsum/dataset/paper_jsons/2020.acl-main.443.json
aclsum/dataset/paper_jsons/2020.acl-main.47.json
aclsum/dataset/paper_jsons/2020.acl-main.528.json
aclsum/dataset/paper_jsons/2020.acl-main.547.json
aclsum/dataset/paper_jsons/2020.acl-main.573.json
aclsum/dataset/paper_jsons/2020.acl-main.642.json
aclsum/dataset/paper_jsons/2020.acl-main.669.json
aclsum/dataset/paper_jsons/2020.acl-main.733.json
aclsum/dataset/paper_jsons/2020.acl-main.75.json
aclsum/dataset/paper_jsons/2020.emnlp-main.298.json
aclsum/dataset/paper_jsons/2020.emnlp-main.308.json
aclsum/dataset/paper_jsons/2020.emnlp-main.384.json
aclsum/dataset/paper_jsons/2020.emnlp-main.500.json
aclsum/dataset/paper_jsons/2020.emnlp-main.505.json
aclsum/dataset/paper_jsons/2021.acl-long.301.json
aclsum/dataset/paper_jsons/2021.acl-long.339.json
aclsum/dataset/paper_jsons/2021.acl-long.420.json
aclsum/dataset/paper_jsons/2021.acl-long.481.json
aclsum/dataset/paper_jsons/2021.acl-long.512.json
aclsum/dataset/paper_jsons/2021.acl-long.57.json
aclsum/dataset/paper_jsons/2021.acl-long.67.json
aclsum/dataset/paper_jsons/2021.eacl-main.102.json
aclsum/dataset/paper_jsons/2021.eacl-main.196.json
aclsum/dataset/paper_jsons/2021.eacl-main.251.json
aclsum/dataset/paper_jsons/2021.eacl-main.84.json
aclsum/dataset/paper_jsons/2021.emnlp-main.185.json
aclsum/dataset/paper_jsons/2021.emnlp-main.284.json
aclsum/dataset/paper_jsons/2021.emnlp-main.411.json
aclsum/dataset/paper_jsons/2021.emnlp-main.424.json
aclsum/dataset/paper_jsons/2021.emnlp-main.66.json
aclsum/dataset/paper_jsons/2021.emnlp-main.765.json
aclsum/dataset/paper_jsons/2021.emnlp-main.767.json
aclsum/dataset/paper_jsons/2021.naacl-main.150.json
aclsum/dataset/paper_jsons/2021.naacl-main.29.json
aclsum-0.1.2.dist-info/RECORD
