Metadata-Version: 2.1
Name: aclsum
Version: 0.1.2
Summary: ACLSum: A New Dataset for Aspect-based Summarization of Scientific Publications
Author-Email: sobamchan <oh.sore.sore.soutarou@gmail.com>
License: MIT
Requires-Python: >=3.11
Requires-Dist: sienna>=0.2.5
